<?xml version='1.0' encoding='utf-8'?>
<thread>
  <submission id="1299493392.0" index="4" link="https://www.reddit.com//r/changemyview/comments/lhonio/cmv_a_better_way_to_pay_for_college_would_be_a/">
    <title>CMV: a better way to pay for college would be a wage percentage system</title>
    <original_poster>SaltySpursSupporter</original_poster>
    <original_post>instead of needing to take out thousands of dollars for student loans, maybe this is a better idea. instead of needing to pay money outright, negotiate a percentage of your future wage. depending on the program you're entering and the amount of years in that system, you can negotiate the percentage and the amount of years. if the person has a minimum wage job for the chosen amount of years, that's still all they get. i'm sure there are problems here that I haven't thought of. you're welcome to change my mind.</original_post>
    </submission>
  <comment id="36216559021.0" user="miguelguajiro" delta="False">
    <text>This already kind of exists. It’s called income based repayment.</text>
    </comment>
  </thread>
